{"type":"FeatureCollection","features":[{"geometry": {"type": "Point", "coordinates": [-87.57049736099998, 30.273220557000002]}, "type": "Feature", "id": 1, "properties": {"": "M", "city": "Orange beach", "name": "Zeke's Landing Marina", "zip": "36561", "url": "http://www.zekeslanding.com/", "photo": "http://sphotos-a.xx.fbcdn.net/hphotos-snc7/426374_344351185603296_804210990_n.jpg", "longitude": -87.57049736, "phone": "(251) 981-4007", "state": "AL", "street": "26619 Perdido Beach Boulevard", "latitude": 30.27322056, "image_tag": "<img src=\"http://sphotos-a.xx.fbcdn.net/hphotos-snc7/426374_344351185603296_804210990_n.jpg\" height=\"160\" width=\"250\" />"}},{"geometry": {"type": "Point", "coordinates": [-88.08704152799999, 30.56751588999998]}, "type": "Feature", "id": 2, "properties": {"": "M", "city": "Mobile", "name": "Dog River Marina", "zip": "36605", "url": "http://www.dogrivermarina.com/home/", "photo": "http://marinas.com/assets/243/dog%20river1.jpg", "longitude": -88.08704153, "phone": "(251) 471-5449", "state": "AL", "street": "5004 Dauphin Island Pkwy", "latitude": 30.56751589, "image_tag": "<img src=\"http://marinas.com/assets/243/dog%20river1.jpg\" height=\"160\" width=\"250\" />"}},{"geometry": {"type": "Point", "coordinates": [-85.81909639600002, 32.739796704000014]}, "type": "Feature", "id": 3, "properties": {"": "M", "city": "Dadeville", "name": "Harbor Pointe Marina", "zip": "36853", "url": "http://harborpointe.net/", "photo": "http://harborpointe.net/wp-content/gallery/marina/217_640x428.jpg", "longitude": -85.8190964, "phone": "(256) 825-0600", "state": "AL", "street": "397 Marina Pointe Road", "latitude": 32.7397967, "image_tag": "<img src=\"http://harborpointe.net/wp-content/gallery/marina/217_640x428.jpg\" height=\"160\" width=\"250\" />"}},{"geometry": {"type": "Point", "coordinates": [-87.98024900000001, 30.90632129300002]}, "type": "Feature", "id": 4, "properties": {"": "M", "city": "Creola", "name": "River Delta Marina", "zip": "36525", "url": "http://www.mobilecountyal.gov/living/parks_river_delta.html", "photo": "http://www.mobilecountyal.gov/photos/Cabins.jpg", "longitude": -87.980249, "phone": "(251) 574-2266", "state": "AL", "street": "2350 Dead Lake Marina Road", "latitude": 30.90632129, "image_tag": "<img src=\"http://www.mobilecountyal.gov/photos/Cabins.jpg\" height=\"160\" width=\"250\" />"}}]}